isogrids/__init__.py
isogrids/env.py
isogrids/environments/__init__.py
isogrids/environments/house_env/__init__.py
isogrids/environments/house_env/build_houses.py
isogrids/environments/house_env/house_furniture.py
isogrids/environments/house_env/house_gen.py
isogrids/environments/house_env/house_gen_timeout.py
isogrids/environments/house_env/house_rooms.py
isogrids-0.0.4.dist-info/LICENSE
isogrids-0.0.4.dist-info/METADATA
isogrids-0.0.4.dist-info/WHEEL
isogrids-0.0.4.dist-info/top_level.txt
isogrids-0.0.4.dist-info/RECORD
